solvis_evaluations_api/__init__.py
solvis_evaluations_api/get_evaluations.py
solvis_evaluations_api-0.1.7.dist-info/METADATA
solvis_evaluations_api-0.1.7.dist-info/WHEEL
solvis_evaluations_api-0.1.7.dist-info/licenses/LICENSE
solvis_evaluations_api-0.1.7.dist-info/RECORD
