Metadata-Version: 2.4
Name: solvis-evaluations-api
Version: 0.1.7
Summary: This is a package for requesting and processing data from Solvis's evaluations API.
Author-email: Paulo Victor <paulo.barbosa@solvis.com.br>
License-File: LICENSE
Requires-Python: >=3.11
Requires-Dist: pandas>=2.2.3
Requires-Dist: requests>=2.32.3
